task3/ram2ports.sv
module ram2ports  #(
    parameter ADDRESS_WIDTH = 8,
              DATA_WIDTH = 8
)(
    input logic     clk,
    input logic     wr_en,
    input logic     rd_en,
    input logic [ADDRESS_WIDTH-1:0] wr_addr,
    input logic [ADDRESS_WIDTH-1:0] rd_addr,
    input logic [DATA_WIDTH-1:0] din,
    output logic [DATA_WIDTH-1:0] dout
);

logic [DATA_WIDTH-1:0] ram_array [2**ADDRESS_WIDTH-1:0];

always_ff @(posedge clk) begin
    if (wr_en)
        ram_array[wr_addr] <= din;
    if (rd_en)
        // output is synchronous
        dout <= ram_array [rd_addr];
end
endmodule

task3/counter.sv
module counter #(
    parameter WIDTH = 8
)(
    input logic clk,
    input logic rst,
    output logic [WIDTH-1:0] count
);

always_ff @ (posedge clk)
    if (rst) count <= {WIDTH{1'b0}};
    else count <= count + 1'b1;
endmodule

task3/sigdelay.sv
module sigdelay #(
    parameter A_WIDTH = 9,
              D_WIDTH = 8
)(
    // interface signals
    input   logic  clk,
    input   logic  rst,
    input   logic  wr,
    input   logic  rd,
    input   logic  [D_WIDTH-1:0]  offset, // offset set by the rotary encoder
    input   logic  [D_WIDTH-1:0]  mic_signal,
    output  logic  [D_WIDTH-1:0]  delayed_signal 
);

logic [A_WIDTH-1:0] addr;

counter #(A_WIDTH) addrCounter (
    .clk (clk),
    .rst (rst),
    .count (addr) // this outputs addr
);

ram2ports #(A_WIDTH, D_WIDTH) audioRam (
    .clk        (clk),
    .wr_en      (wr),
    .rd_en      (rd),
    .wr_addr    (addr), // uses the counter output, writes mic_signal to this address
    .rd_addr    (addr - offset), // reads at addr - offset
    .din        (mic_signal), 
    .dout       (delayed_signal) // only output
);
endmodule

task3/sigdelay.vcd
$version Generated by VerilatedVcd $end
$date Tue Nov 12 23:51:07 2024 $end
$timescale 1ps $end

 $scope module TOP $end
  $var wire  1 # clk $end
  $var wire  8 ) delayed_signal [7:0] $end
  $var wire  8 ( mic_signal [7:0] $end
  $var wire  8 ' offset [7:0] $end
  $var wire  1 & rd $end
  $var wire  1 $ rst $end
  $var wire  1 % wr $end
  $scope module sigdelay $end
   $var wire 32 , A_WIDTH [31:0] $end
   $var wire 32 - D_WIDTH [31:0] $end
   $var wire  9 * addr [8:0] $end
   $var wire  1 # clk $end
   $var wire  8 ) delayed_signal [7:0] $end
   $var wire  8 ( mic_signal [7:0] $end
   $var wire  8 ' offset [7:0] $end
   $var wire  1 & rd $end
   $var wire  1 $ rst $end
   $var wire  1 % wr $end
   $scope module addrCounter $end
    $var wire 32 , WIDTH [31:0] $end
    $var wire  1 # clk $end
    $var wire  9 * count [8:0] $end
    $var wire  1 $ rst $end
   $upscope $end
   $scope module audioRam $end
    $var wire 32 , ADDRESS_WIDTH [31:0] $end
    $var wire 32 - DATA_WIDTH [31:0] $end
    $var wire  1 # clk $end
    $var wire  8 ( din [7:0] $end
    $var wire  8 ) dout [7:0] $end
    $var wire  9 + rd_addr [8:0] $end
    $var wire  1 & rd_en $end
    $var wire  9 * wr_addr [8:0] $end
    $var wire  1 % wr_en $end
   $upscope $end
  $upscope $end
 $upscope $end
$enddefinitions $end


#0
1#
0$
1%
1&
b01000000 '
b00000000 (
b00000000 )
b000000000 *
b111000000 +
b00000000000000000000000000001001 ,
b00000000000000000000000000001000 -
#1
0#
#2
1#
b00110011 '
b01101100 (
b000000001 *
b111001110 +
#3
0#
#4
1#
b000000010 *
b111001111 +
#5
0#
#6
1#
b01101010 (
b000000011 *
b111010000 +
#7
0#
#8
1#
b01101110 (
b000000100 *
b111010001 +
#9
0#
#10
1#
b01101010 (
b000000101 *
b111010010 +
#11
0#
#12
1#
b000000110 *
b111010011 +
#13
0#
#14
1#
b000000111 *
b111010100 +
#15
0#
#16
1#
b01101100 (
b000001000 *
b111010101 +
#17
0#
#18
1#
b01101011 (
b000001001 *
b111010110 +
#19
0#
#20
1#
b01101010 (
b000001010 *
b111010111 +
#21
0#
#22
1#
b01101100 (
b000001011 *
b111011000 +
#23
0#
#24
1#
b000001100 *
b111011001 +
#25
0#
#26
1#
b01101010 (
b000001101 *
b111011010 +
#27
0#
#28
1#
b01101101 (
b000001110 *
b111011011 +
#29
0#
#30
1#
b01101100 (
b000001111 *
b111011100 +
#31
0#
#32
1#
b000010000 *
b111011101 +
#33
0#
#34
1#
b01101011 (
b000010001 *
b111011110 +
#35
0#
#36
1#
b000010010 *
b111011111 +
#37
0#
#38
1#
b01101100 (
b000010011 *
b111100000 +
#39
0#
#40
1#
b01101010 (
b000010100 *
b111100001 +
#41
0#
#42
1#
b01101100 (
b000010101 *
b111100010 +
#43
0#
#44
1#
b000010110 *
b111100011 +
#45
0#
#46
1#
b01101101 (
b000010111 *
b111100100 +
#47
0#
#48
1#
b01101100 (
b000011000 *
b111100101 +
#49
0#
#50
1#
b01101011 (
b000011001 *
b111100110 +
#51
0#
#52
1#
b01101100 (
b000011010 *
b111100111 +
#53
0#
#54
1#
b01101101 (
b000011011 *
b111101000 +
#55
0#
#56
1#
b01101011 (
b000011100 *
b111101001 +
#57
0#
#58
1#
b01101110 (
b000011101 *
b111101010 +
#59
0#
#60
1#
b01101010 (
b000011110 *
b111101011 +
#61
0#
#62
1#
b01101100 (
b000011111 *
b111101100 +
#63
0#
#64
1#
b000100000 *
b111101101 +
#65
0#
#66
1#
b01101101 (
b000100001 *
b111101110 +
#67
0#
#68
1#
b01101010 (
b000100010 *
b111101111 +
#69
0#
#70
1#
b01101011 (
b000100011 *
b111110000 +
#71
0#
#72
1#
b01101101 (
b000100100 *
b111110001 +
#73
0#
#74
1#
b01101011 (
b000100101 *
b111110010 +
#75
0#
#76
1#
b01101100 (
b000100110 *
b111110011 +
#77
0#
#78
1#
b01101011 (
b000100111 *
b111110100 +
#79
0#
#80
1#
b01101100 (
b000101000 *
b111110101 +
#81
0#
#82
1#
b01101101 (
b000101001 *
b111110110 +
#83
0#
#84
1#
b01101100 (
b000101010 *
b111110111 +
#85
0#
#86
1#
b01101011 (
b000101011 *
b111111000 +
#87
0#
#88
1#
b01101100 (
b000101100 *
b111111001 +
#89
0#
#90
1#
b000101101 *
b111111010 +
#91
0#
#92
1#
b01101010 (
b000101110 *
b111111011 +
#93
0#
#94
1#
b01101011 (
b000101111 *
b111111100 +
#95
0#
#96
1#
b01101111 (
b000110000 *
b111111101 +
#97
0#
#98
1#
b000110001 *
b111111110 +
#99
0#
#100
1#
b01101100 (
b000110010 *
b111111111 +
#101
0#
#102
1#
b01101110 (
b000110011 *
b000000000 +
#103
0#
#104
1#
b01101010 (
b000110100 *
b000000001 +
#105
0#
#106
1#
b01101100 (
b01101100 )
b000110101 *
b000000010 +
#107
0#
#108
1#
b01101010 (
b000110110 *
b000000011 +
#109
0#
#110
1#
b01101101 (
b01101010 )
b000110111 *
b000000100 +
#111
0#
#112
1#
b01101110 (
b01101110 )
b000111000 *
b000000101 +
#113
0#
#114
1#
b01101001 (
b01101010 )
b000111001 *
b000000110 +
#115
0#
#116
1#
b01101100 (
b000111010 *
b000000111 +
#117
0#
#118
1#
b01101010 (
b000111011 *
b000001000 +
#119
0#
#120
1#
b01101100 (
b01101100 )
b000111100 *
b000001001 +
#121
0#
#122
1#
b01101011 (
b01101011 )
b000111101 *
b000001010 +
#123
0#
#124
1#
b01101010 )
b000111110 *
b000001011 +
#125
0#
#126
1#
b01101100 )
b000111111 *
b000001100 +
#127
0#
#128
1#
b01101100 (
b001000000 *
b000001101 +
#129
0#
#130
1#
b01101011 (
b01101010 )
b001000001 *
b000001110 +
#131
0#
#132
1#
b01101101 )
b001000010 *
b000001111 +
#133
0#
#134
1#
b01101000 (
b01101100 )
b001000011 *
b000010000 +
#135
0#
#136
1#
b01101100 (
b001000100 *
b000010001 +
#137
0#
#138
1#
b01101010 (
b01101011 )
b001000101 *
b000010010 +
#139
0#
#140
1#
b001000110 *
b000010011 +
#141
0#
#142
1#
b01101100 )
b001000111 *
b000010100 +
#143
0#
#144
1#
b01101000 (
b01101010 )
b001001000 *
b000010101 +
#145
0#
#146
1#
b01101001 (
b01101100 )
b001001001 *
b000010110 +
#147
0#
#148
1#
b01101010 (
b001001010 *
b000010111 +
#149
0#
#150
1#
b01101000 (
b01101101 )
b001001011 *
b000011000 +
#151
0#
#152
1#
b01101010 (
b01101100 )
b001001100 *
b000011001 +
#153
0#
#154
1#
b01101011 )
b001001101 *
b000011010 +
#155
0#
#156
1#
b01101100 )
b001001110 *
b000011011 +
#157
0#
#158
1#
b01101011 (
b01101101 )
b001001111 *
b000011100 +
#159
0#
#160
1#
b01101001 (
b01101011 )
b001010000 *
b000011101 +
#161
0#
#162
1#
b01101000 (
b01101110 )
b001010001 *
b000011110 +
#163
0#
#164
1#
b01101011 (
b01101010 )
b001010010 *
b000011111 +
#165
0#
#166
1#
b01101001 (
b01101100 )
b001010011 *
b000100000 +
#167
0#
#168
1#
b001010100 *
b000100001 +
#169
0#
#170
1#
b01101000 (
b01101101 )
b001010101 *
b000100010 +
#171
0#
#172
1#
b01101011 (
b01101010 )
b001010110 *
b000100011 +
#173
0#
#174
1#
b01101100 (
b01101011 )
b001010111 *
b000100100 +
#175
0#
#176
1#
b01101011 (
b01101101 )
b001011000 *
b000100101 +
#177
0#
#178
1#
b01101011 )
b001011001 *
b000100110 +
#179
0#
#180
1#
b01101001 (
b01101100 )
b001011010 *
b000100111 +
#181
0#
#182
1#
b01101011 (
b01101011 )
b001011011 *
b000101000 +
#183
0#
#184
1#
b01101010 (
b01101100 )
b001011100 *
b000101001 +
#185
0#
#186
1#
b01101101 )
b001011101 *
b000101010 +
#187
0#
#188
1#
b01101011 (
b01101100 )
b001011110 *
b000101011 +
#189
0#
#190
1#
b01101011 )
b001011111 *
b000101100 +
#191
0#
#192
1#
b01101111 (
b01101100 )
b001100000 *
b000101101 +
#193
0#
#194
1#
b01101100 (
b001100001 *
b000101110 +
#195
0#
#196
1#
b01101011 (
b01101010 )
b001100010 *
b000101111 +
#197
0#
#198
1#
b01101100 (
b01101011 )
b001100011 *
b000110000 +
#199
0#
#200
1#
b01101111 )
b001100100 *
b000110001 +
#201
0#
#202
1#
b01101010 (
b001100101 *
b000110010 +
#203
0#
#204
1#
b01101100 )
b001100110 *
b000110011 +
#205
0#
#206
1#
b01101110 )
b001100111 *
b000110100 +
#207
0#
#208
1#
b01101100 (
b01101010 )
b001101000 *
b000110101 +
#209
0#
#210
1#
b01101001 (
b01101100 )
b001101001 *
b000110110 +
#211
0#
#212
1#
b01101000 (
b01101010 )
b001101010 *
b000110111 +
#213
0#
#214
1#
b01101011 (
b01101101 )
b001101011 *
b000111000 +
#215
0#
#216
1#
b01101100 (
b01101110 )
b001101100 *
b000111001 +
#217
0#
#218
1#
b01101000 (
b01101001 )
b001101101 *
b000111010 +
#219
0#
#220
1#
b01101001 (
b01101100 )
b001101110 *
b000111011 +
#221
0#
#222
1#
b01101100 (
b01101010 )
b001101111 *
b000111100 +
#223
0#
#224
1#
b01101010 (
b01101100 )
b001110000 *
b000111101 +
#225
0#
#226
1#
b01101111 (
b01101011 )
b001110001 *
b000111110 +
#227
0#
#228
1#
b01101100 (
b001110010 *
b000111111 +
#229
0#
#230
1#
b01101101 (
b001110011 *
b001000000 +
#231
0#
#232
1#
b01101110 (
b01101100 )
b001110100 *
b001000001 +
#233
0#
#234
1#
b01101101 (
b01101011 )
b001110101 *
b001000010 +
#235
0#
#236
1#
b01110000 (
b001110110 *
b001000011 +
#237
0#
#238
1#
b01101111 (
b01101000 )
b001110111 *
b001000100 +
#239
0#
#240
1#
b01101100 )
b001111000 *
b001000101 +
#241
0#
#242
1#
b01101001 (
b01101010 )
b001111001 *
b001000110 +
#243
0#
#244
1#
b01110001 (
b001111010 *
b001000111 +
#245
0#
#246
1#
b01101110 (
b001111011 *
b001001000 +
#247
0#
#248
1#
b01101111 (
b01101000 )
b001111100 *
b001001001 +
#249
0#
#250
1#
b01101001 )
b001111101 *
b001001010 +
#251
0#
#252
1#
b01101110 (
b01101010 )
b001111110 *
b001001011 +
#253
0#
#254
1#
b01101000 )
b001111111 *
b001001100 +
#255
0#
#256
1#
b01101010 )
b010000000 *
b001001101 +
#257
0#
#258
1#
b010000001 *
b001001110 +
#259
0#
#260
1#
b010000010 *
b001001111 +
#261
0#
#262
1#
b01101101 (
b01101011 )
b010000011 *
b001010000 +
#263
0#
#264
1#
b01101111 (
b01101001 )
b010000100 *
b001010001 +
#265
0#
#266
1#
b01101110 (
b01101000 )
b010000101 *
b001010010 +
#267
0#
#268
1#
b01101100 (
b01101011 )
b010000110 *
b001010011 +
#269
0#
#270
1#
b01101001 )
b010000111 *
b001010100 +
#271
0#
#272
1#
b01101110 (
b010001000 *
b001010101 +
#273
0#
#274
1#
b01101111 (
b01101000 )
b010001001 *
b001010110 +
#275
0#
#276
1#
b01101011 (
b01101011 )
b010001010 *
b001010111 +
#277
0#
#278
1#
b01101110 (
b01101100 )
b010001011 *
b001011000 +
#279
0#
#280
1#
b01101100 (
b01101011 )
b010001100 *
b001011001 +
#281
0#
#282
1#
b010001101 *
b001011010 +
#283
0#
#284
1#
b01101101 (
b01101001 )
b010001110 *
b001011011 +
#285
0#
#286
1#
b01101011 )
b010001111 *
b001011100 +
#287
0#
#288
1#
b01101011 (
b01101010 )
b010010000 *
b001011101 +
#289
0#
#290
1#
b01101100 (
b010010001 *
b001011110 +
#291
0#
#292
1#
b01101011 )
b010010010 *
b001011111 +
#293
0#
#294
1#
b010010011 *
b001100000 +
#295
0#
#296
1#
b01101011 (
b01101111 )
b010010100 *
b001100001 +
#297
0#
#298
1#
b01110000 (
b01101100 )
b010010101 *
b001100010 +
#299
0#
#300
1#
b01101101 (
b01101011 )
b010010110 *
b001100011 +
#301
0#
#302
1#
b01101100 (
b01101100 )
b010010111 *
b001100100 +
#303
0#
#304
1#
b01101111 (
b010011000 *
b001100101 +
#305
0#
#306
1#
b01101110 (
b01101010 )
b010011001 *
b001100110 +
#307
0#
#308
1#
b01101101 (
b010011010 *
b001100111 +
#309
0#
#310
1#
b010011011 *
b001101000 +
#311
0#
#312
1#
b01101100 (
b01101100 )
b010011100 *
b001101001 +
#313
0#
#314
1#
b01101111 (
b01101001 )
b010011101 *
b001101010 +
#315
0#
#316
1#
b01101100 (
b01101000 )
b010011110 *
b001101011 +
#317
0#
#318
1#
b01101011 )
b010011111 *
b001101100 +
#319
0#
#320
1#
b01101111 (
b01101100 )
b010100000 *
b001101101 +
#321
0#
#322
1#
b01101101 (
b01101000 )
b010100001 *
b001101110 +
#323
0#
#324
1#
b01101001 )
b010100010 *
b001101111 +
#325
0#
#326
1#
b01101011 (
b01101100 )
b010100011 *
b001110000 +
#327
0#
#328
1#
b01100111 (
b01101010 )
b010100100 *
b001110001 +
#329
0#
#330
1#
b01101011 (
b01101111 )
b010100101 *
b001110010 +
#331
0#
#332
1#
b01101010 (
b01101100 )
b010100110 *
b001110011 +
#333
0#
#334
1#
b01101101 )
b010100111 *
b001110100 +
#335
0#
#336
1#
b01100111 (
b01101110 )
b010101000 *
b001110101 +
#337
0#
#338
1#
b01101010 (
b01101101 )
b010101001 *
b001110110 +
#339
0#
#340
1#
b01101001 (
b01110000 )
b010101010 *
b001110111 +
#341
0#
#342
1#
b01101011 (
b01101111 )
b010101011 *
b001111000 +
#343
0#
#344
1#
b01100111 (
b010101100 *
b001111001 +
#345
0#
#346
1#
b01101001 (
b01101001 )
b010101101 *
b001111010 +
#347
0#
#348
1#
b01101000 (
b01110001 )
b010101110 *
b001111011 +
#349
0#
#350
1#
b01101001 (
b01101110 )
b010101111 *
b001111100 +
#351
0#
#352
1#
b01101111 )
b010110000 *
b001111101 +
#353
0#
#354
1#
b01101010 (
b010110001 *
b001111110 +
#355
0#
#356
1#
b01101000 (
b01101110 )
b010110010 *
b001111111 +
#357
0#
#358
1#
b01101001 (
b010110011 *
b010000000 +
#359
0#
#360
1#
b01101011 (
b010110100 *
b010000001 +
#361
0#
#362
1#
b010110101 *
b010000010 +
#363
0#
#364
1#
b01101010 (
b010110110 *
b010000011 +
#365
0#
#366
1#
b01101000 (
b01101101 )
b010110111 *
b010000100 +
#367
0#
#368
1#
b01101101 (
b01101111 )
b010111000 *
b010000101 +
#369
0#
#370
1#
b01101010 (
b01101110 )
b010111001 *
b010000110 +
#371
0#
#372
1#
b01101100 )
b010111010 *
b010000111 +
#373
0#
#374
1#
b01101001 (
b010111011 *
b010001000 +
#375
0#
#376
1#
b01101100 (
b01101110 )
b010111100 *
b010001001 +
#377
0#
#378
1#
b01101011 (
b01101111 )
b010111101 *
b010001010 +
#379
0#
#380
1#
b00110100 '
b01101100 (
b01101011 )
b010111110 *
#381
0#
#382
1#
b01101001 (
b010111111 *
b010001011 +
#383
0#
#384
1#
b00110101 '
b01101011 (
b01101110 )
b011000000 *
#385
0#
#386
1#
b00110110 '
b011000001 *
#387
0#
#388
1#
b00111001 '
b011000010 *
b010001001 +
#389
0#
#390
1#
b00111110 '
b01101111 (
b01101111 )
b011000011 *
b010000101 +
#391
0#
#392
1#
b01000001 '
b01101011 (
b01101110 )
b011000100 *
b010000011 +
#393
0#
#394
1#
b01000011 '
b01101010 (
b01101101 )
b011000101 *
b010000010 +
#395
0#
#396
1#
b01101101 (
b01101110 )
b011000110 *
b010000011 +
#397
0#
#398
1#
b01101001 (
b01101101 )
b011000111 *
b010000100 +
#399
0#
#400
1#
b01101100 (
b01101111 )
b011001000 *
b010000101 +
#401
0#
#402
1#
b01101001 (
b01101110 )
b011001001 *
b010000110 +
#403
0#
#404
1#
b01101010 (
b01101100 )
b011001010 *
b010000111 +
#405
0#
#406
1#
b011001011 *
b010001000 +
#407
0#
#408
1#
b01101011 (
b01101110 )
b011001100 *
b010001001 +
#409
0#
#410
1#
b01101001 (
b01101111 )
b011001101 *
b010001010 +
#411
0#
#412
1#
b01101011 (
b01101011 )
b011001110 *
b010001011 +
#413
0#
#414
1#
b01101010 (
b01101110 )
b011001111 *
b010001100 +
#415
0#
#416
1#
b01101100 (
b01101100 )
b011010000 *
b010001101 +
#417
0#
#418
1#
b01101001 (
b011010001 *
b010001110 +
#419
0#
#420
1#
b01101000 (
b01101101 )
b011010010 *
b010001111 +
#421
0#
#422
1#
b01101100 (
b011010011 *
b010010000 +
#423
0#
#424
1#
b01101011 (
b01101011 )
b011010100 *
b010010001 +
#425
0#
#426
1#
b01101100 )
b011010101 *
b010010010 +
#427
0#
#428
1#
b01101010 (
b011010110 *
b010010011 +
#429
0#
#430
1#
b011010111 *
b010010100 +
#431
0#
#432
1#
b01101101 (
b01101011 )
b011011000 *
b010010101 +
#433
0#
#434
1#
b01101011 (
b01110000 )
b011011001 *
b010010110 +
#435
0#
#436
1#
b01101100 (
b01101101 )
b011011010 *
b010010111 +
#437
0#
#438
1#
b01101101 (
b01101100 )
b011011011 *
b010011000 +
#439
0#
#440
1#
b01101011 (
b01101111 )
b011011100 *
b010011001 +
#441
0#
#442
1#
b01101100 (
b01101110 )
b011011101 *
b010011010 +
#443
0#
#444
1#
b01101011 (
b01101101 )
b011011110 *
b010011011 +
#445
0#
#446
1#
b01101110 (
b011011111 *
b010011100 +
#447
0#
#448
1#
b01101100 )
b011100000 *
b010011101 +
#449
0#
#450
1#
b01101101 (
b01101111 )
b011100001 *
b010011110 +
#451
0#
#452
1#
b01101111 (
b01101100 )
b011100010 *
b010011111 +
#453
0#
#454
1#
b01101110 (
b011100011 *
b010100000 +
#455
0#
#456
1#
b01101111 (
b01101111 )
b011100100 *
b010100001 +
#457
0#
#458
1#
b01101110 (
b01101101 )
b011100101 *
b010100010 +
#459
0#
#460
1#
b01101100 (
b011100110 *
b010100011 +
#461
0#
#462
1#
b01101101 (
b01101011 )
b011100111 *
b010100100 +
#463
0#
#464
1#
b01100111 )
b011101000 *
b010100101 +
#465
0#
#466
1#
b01101100 (
b01101011 )
b011101001 *
b010100110 +
#467
0#
#468
1#
b01101010 )
b011101010 *
b010100111 +
#469
0#
#470
1#
b01101110 (
b011101011 *
b010101000 +
#471
0#
#472
1#
b01101111 (
b01100111 )
b011101100 *
b010101001 +
#473
0#
#474
1#
b01101100 (
b01101010 )
b011101101 *
b010101010 +
#475
0#
#476
1#
b01101011 (
b01101001 )
b011101110 *
b010101011 +
#477
0#
#478
1#
b01101001 (
b01101011 )
b011101111 *
b010101100 +
#479
0#
#480
1#
b01101010 (
b01100111 )
b011110000 *
b010101101 +
#481
0#
#482
1#
b01101011 (
b01101001 )
b011110001 *
b010101110 +
#483
0#
#484
1#
b01101010 (
b01101000 )
b011110010 *
b010101111 +
#485
0#
#486
1#
b01101011 (
b01101001 )
b011110011 *
b010110000 +
#487
0#
#488
1#
b011110100 *
b010110001 +
#489
0#
#490
1#
b01101010 (
b01101010 )
b011110101 *
b010110010 +
#491
0#
#492
1#
b01101001 (
b01101000 )
b011110110 *
b010110011 +
#493
0#
#494
1#
b01101101 (
b01101001 )
b011110111 *
b010110100 +
#495
0#
#496
1#
b01101010 (
b01101011 )
b011111000 *
b010110101 +
#497
0#
#498
1#
b011111001 *
b010110110 +
#499
0#
#500
1#
b01101001 (
b01101010 )
b011111010 *
b010110111 +
#501
0#
#502
1#
b01101101 (
b01101000 )
b011111011 *
b010111000 +
#503
0#
#504
1#
b01101101 )
b011111100 *
b010111001 +
#505
0#
#506
1#
b01101010 (
b01101010 )
b011111101 *
b010111010 +
#507
0#
#508
1#
b01101100 (
b011111110 *
b010111011 +
#509
0#
#510
1#
b01101001 )
b011111111 *
b010111100 +
#511
0#
#512
1#
b01101011 (
b01101100 )
b100000000 *
b010111101 +
#513
0#
#514
1#
b01101100 (
b01101011 )
b100000001 *
b010111110 +
#515
0#
#516
1#
b01101110 (
b01101100 )
b100000010 *
b010111111 +
#517
0#
#518
1#
b01101100 (
b01101001 )
b100000011 *
b011000000 +
#519
0#
#520
1#
b01101101 (
b01101011 )
b100000100 *
b011000001 +
#521
0#
#522
1#
b100000101 *
b011000010 +
#523
0#
#524
1#
b01101111 (
b100000110 *
b011000011 +
#525
0#
#526
1#
b01101110 (
b01101111 )
b100000111 *
b011000100 +
#527
0#
#528
1#
b01101011 (
b01101011 )
b100001000 *
b011000101 +
#529
0#
#530
1#
b01101100 (
b01101010 )
b100001001 *
b011000110 +
#531
0#
#532
1#
b01101101 (
b01101101 )
b100001010 *
b011000111 +
#533
0#
#534
1#
b01101011 (
b01101001 )
b100001011 *
b011001000 +
#535
0#
#536
1#
b01101100 (
b01101100 )
b100001100 *
b011001001 +
#537
0#
#538
1#
b01101000 (
b01101001 )
b100001101 *
b011001010 +
#539
0#
#540
1#
b01101101 (
b01101010 )
b100001110 *
b011001011 +
#541
0#
#542
1#
b01101100 (
b100001111 *
b011001100 +
#543
0#
#544
1#
b01101111 (
b01101011 )
b100010000 *
b011001101 +
#545
0#
#546
1#
b01101100 (
b01101001 )
b100010001 *
b011001110 +
#547
0#
#548
1#
b01101101 (
b01101011 )
b100010010 *
b011001111 +
#549
0#
#550
1#
b01101011 (
b01101010 )
b100010011 *
b011010000 +
#551
0#
#552
1#
b01101101 (
b01101100 )
b100010100 *
b011010001 +
#553
0#
#554
1#
b01101011 (
b01101001 )
b100010101 *
b011010010 +
#555
0#
#556
1#
b01101000 )
b100010110 *
b011010011 +
#557
0#
#558
1#
b01101100 )
b100010111 *
b011010100 +
#559
0#
#560
1#
b01101010 (
b01101011 )
b100011000 *
b011010101 +
#561
0#
#562
1#
b100011001 *
b011010110 +
#563
0#
#564
1#
b01101011 (
b01101010 )
b100011010 *
b011010111 +
#565
0#
#566
1#
b01101010 (
b100011011 *
b011011000 +
#567
0#
#568
1#
b01101011 (
b01101101 )
b100011100 *
b011011001 +
#569
0#
#570
1#
b01101011 )
b100011101 *
b011011010 +
#571
0#
#572
1#
b01101001 (
b01101100 )
b100011110 *
b011011011 +
#573
0#
#574
1#
b01101010 (
b01101101 )
b100011111 *
b011011100 +
#575
0#
#576
1#
b01101011 (
b01101011 )
b100100000 *
b011011101 +
#577
0#
#578
1#
b01101010 (
b01101100 )
b100100001 *
b011011110 +
#579
0#
#580
1#
b01101011 )
b100100010 *
b011011111 +
#581
0#
#582
1#
b01101011 (
b01101110 )
b100100011 *
b011100000 +
#583
0#
#584
1#
b01101101 (
b100100100 *
b011100001 +
#585
0#
#586
1#
b01101110 (
b01101101 )
b100100101 *
b011100010 +
#587
0#
#588
1#
b01101111 )
b100100110 *
b011100011 +
#589
0#
#590
1#
b01101110 )
b100100111 *
b011100100 +
#591
0#
#592
1#
b01101111 )
b100101000 *
b011100101 +
#593
0#
#594
1#
b01101101 (
b01101110 )
b100101001 *
b011100110 +
#595
0#
#596
1#
b01101100 )
b100101010 *
b011100111 +
#597
0#
#598
1#
b01101110 (
b01101101 )
b100101011 *
b011101000 +
#599
0#
#600
1#
b01101111 (
b100101100 *
b011101001 +
#601
0#
#602
1#
b01101100 )
b100101101 *
b011101010 +
#603
0#
#604
1#
b01110001 (
b100101110 *
b011101011 +
#605
0#
#606
1#
b01101111 (
b01101110 )
b100101111 *
b011101100 +
#607
0#
#608
1#
b01101111 )
b100110000 *
b011101101 +
#609
0#
#610
1#
b01101011 (
b01101100 )
b100110001 *
b011101110 +
#611
0#
#612
1#
b01101110 (
b01101011 )
b100110010 *
b011101111 +
#613
0#
#614
1#
b01101011 (
b01101001 )
b100110011 *
b011110000 +
#615
0#
#616
1#
b01101101 (
b01101010 )
b100110100 *
b011110001 +
#617
0#
#618
1#
b01101100 (
b01101011 )
b100110101 *
b011110010 +
#619
0#
#620
1#
b01101101 (
b01101010 )
b100110110 *
b011110011 +
#621
0#
#622
1#
b01101100 (
b01101011 )
b100110111 *
b011110100 +
#623
0#
#624
1#
b01101101 (
b100111000 *
b011110101 +
#625
0#
#626
1#
b01101011 (
b01101010 )
b100111001 *
b011110110 +
#627
0#
#628
1#
b01101001 )
b100111010 *
b011110111 +
#629
0#
#630
1#
b01101010 (
b01101101 )
b100111011 *
b011111000 +
#631
0#
#632
1#
b01101010 )
b100111100 *
b011111001 +
#633
0#
#634
1#
b01101100 (
b100111101 *
b011111010 +
#635
0#
#636
1#
b01101001 )
b100111110 *
b011111011 +
#637
0#
#638
1#
b01101011 (
b01101101 )
b100111111 *
b011111100 +
#639
0#
#640
1#
b01101100 (
b101000000 *
b011111101 +
#641
0#
#642
1#
b01101101 (
b01101010 )
b101000001 *
b011111110 +
#643
0#
#644
1#
b01101100 )
b101000010 *
b011111111 +
#645
0#
#646
1#
b01101010 (
b101000011 *
b100000000 +
#647
0#
#648
1#
b01101011 )
b101000100 *
b100000001 +
#649
0#
#650
1#
b01101100 (
b01101100 )
b101000101 *
b100000010 +
#651
0#
#652
1#
b01101101 (
b01101110 )
b101000110 *
b100000011 +
#653
0#
#654
1#
b01101110 (
b01101100 )
b101000111 *
b100000100 +
#655
0#
#656
1#
b01101101 (
b01101101 )
b101001000 *
b100000101 +
#657
0#
#658
1#
b101001001 *
b100000110 +
#659
0#
#660
1#
b01101010 (
b01101111 )
b101001010 *
b100000111 +
#661
0#
#662
1#
b01101110 )
b101001011 *
b100001000 +
#663
0#
#664
1#
b01101001 (
b01101011 )
b101001100 *
b100001001 +
#665
0#
#666
1#
b01101011 (
b01101100 )
b101001101 *
b100001010 +
#667
0#
#668
1#
b01101101 (
b01101101 )
b101001110 *
b100001011 +
#669
0#
#670
1#
b01101100 (
b01101011 )
b101001111 *
b100001100 +
#671
0#
#672
1#
b01101011 (
b01101100 )
b101010000 *
b100001101 +
#673
0#
#674
1#
b01101000 )
b101010001 *
b100001110 +
#675
0#
#676
1#
b01101100 (
b01101101 )
b101010010 *
b100001111 +
#677
0#
#678
1#
b01101011 (
b01101100 )
b101010011 *
b100010000 +
#679
0#
#680
1#
b01101000 (
b01101111 )
b101010100 *
b100010001 +
#681
0#
#682
1#
b01101011 (
b01101100 )
b101010101 *
b100010010 +
#683
0#
#684
1#
b01101101 )
b101010110 *
b100010011 +
#685
0#
#686
1#
b01101011 )
b101010111 *
b100010100 +
#687
0#
#688
1#
b01101100 (
b01101101 )
b101011000 *
b100010101 +
#689
0#
#690
1#
b01101000 (
b01101011 )
b101011001 *
b100010110 +
#691
0#
#692
1#
b01101010 (
b101011010 *
b100010111 +
#693
0#
#694
1#
b01101000 (
b101011011 *
b100011000 +
#695
0#
#696
1#
b01101010 )
b101011100 *
b100011001 +
#697
0#
#698
1#
b01101001 (
b101011101 *
b100011010 +
#699
0#
#700
1#
b01101010 (
b01101011 )
b101011110 *
b100011011 +
#701
0#
#702
1#
b01101010 )
b101011111 *
b100011100 +
#703
0#
#704
1#
b01101011 )
b101100000 *
b100011101 +
#705
0#
#706
1#
b01101000 (
b101100001 *
b100011110 +
#707
0#
#708
1#
b01101001 (
b01101001 )
b101100010 *
b100011111 +
#709
0#
#710
1#
b01101000 (
b01101010 )
b101100011 *
b100100000 +
#711
0#
#712
1#
b01101010 (
b01101011 )
b101100100 *
b100100001 +
#713
0#
#714
1#
b01101010 )
b101100101 *
b100100010 +
#715
0#
#716
1#
b01101001 (
b101100110 *
b100100011 +
#717
0#
#718
1#
b01101000 (
b01101011 )
b101100111 *
b100100100 +
#719
0#
#720
1#
b01101011 (
b01101101 )
b101101000 *
b100100101 +
#721
0#
#722
1#
b01101010 (
b01101110 )
b101101001 *
b100100110 +
#723
0#
#724
1#
b01101100 (
b101101010 *
b100100111 +
#725
0#
#726
1#
b01101011 (
b101101011 *
b100101000 +
#727
0#
#728
1#
b01101000 (
b101101100 *
b100101001 +
#729
0#
#730
1#
b01101011 (
b01101101 )
b101101101 *
b100101010 +
#731
0#
#732
1#
b101101110 *
b100101011 +
#733
0#
#734
1#
b01101010 (
b01101110 )
b101101111 *
b100101100 +
#735
0#
