task2/rom.sv
module rom #(
    parameter ADDRESS_WIDTH = 8,
              DATA_WIDTH = 8
)(
    input logic clk,
    input logic [ADDRESS_WIDTH-1:0] addr,
    output logic [DATA_WIDTH-1:0] dout1,
    output logic [DATA_WIDTH-1:0] dout2
);

logic [DATA_WIDTH-1:0] rom_array [2**ADDRESS_WIDTH-1:0];

initial begin
        $display("Loading rom.");
        $readmemh("sinerom.mem", rom_array);
end;

always_ff @(posedge clk)
    // output is synchronous
    begin
        dout1 <= rom_array [addr];
        dout2 <= rom_array [addr + 7'd64];
    end
endmodule

task1/counter.sv
module counter #(
    parameter WIDTH = 8
)(
    input logic clk,
    input logic rst,
    input logic en,
    input logic [WIDTH-1:0] incr,
    output logic [WIDTH-1:0] count
);

always_ff @ (posedge clk)
    if (rst) count <= {WIDTH{1'b0}};
    else if (en) count <= count + incr;
    else count <= count + {WIDTH{1'b0}};
endmodule

task2/sinegen.sv
module sinegen #(
    parameter A_WIDTH = 8,
              D_WIDTH = 8
)(
    input logic clk,
    input logic rst,
    input logic en,
    input logic [D_WIDTH-1:0] incr,
    output logic [D_WIDTH-1:0] dout1,
    output logic [D_WIDTH-1:0] dout2
);

    logic [A_WIDTH:0] address; // interconnect wire

counter addrCounter (
    .clk (clk),
    .rst (rst),
    .en (en),
    .incr (incr),
    .count (address)
);

rom sineRom (
    .clk (clk),
    .addr (address),
    .dout1 (dout1),
    .dout2 (dout2)
);

endmodule

task2/sinegen.vcd
$version Generated by VerilatedVcd $end
$date Fri Oct 25 12:03:55 2024 $end
$timescale 1ps $end

 $scope module TOP $end
  $var wire  1 # clk $end
  $var wire  8 ' dout1 [7:0] $end
  $var wire  8 ( dout2 [7:0] $end
  $var wire  1 % en $end
  $var wire  8 & incr [7:0] $end
  $var wire  1 $ rst $end
  $scope module sinegen $end
   $var wire 32 + A_WIDTH [31:0] $end
   $var wire 32 + D_WIDTH [31:0] $end
   $var wire  9 ) address [8:0] $end
   $var wire  1 # clk $end
   $var wire  8 ' dout1 [7:0] $end
   $var wire  8 ( dout2 [7:0] $end
   $var wire  1 % en $end
   $var wire  8 & incr [7:0] $end
   $var wire  1 $ rst $end
   $scope module addrCounter $end
    $var wire 32 + WIDTH [31:0] $end
    $var wire  1 # clk $end
    $var wire  8 * count [7:0] $end
    $var wire  1 % en $end
    $var wire  8 & incr [7:0] $end
    $var wire  1 $ rst $end
   $upscope $end
   $scope module sineRom $end
    $var wire 32 + ADDRESS_WIDTH [31:0] $end
    $var wire 32 + DATA_WIDTH [31:0] $end
    $var wire  8 * addr [7:0] $end
    $var wire  1 # clk $end
    $var wire  8 ' dout1 [7:0] $end
    $var wire  8 ( dout2 [7:0] $end
   $upscope $end
  $upscope $end
 $upscope $end
$enddefinitions $end


#0
1#
0$
1%
b00000001 &
b00000000 '
b00000000 (
b000000000 )
b00000000 *
b00000000000000000000000000001000 +
#1
0#
#2
1#
b00010111 &
b11111110 '
b01111110 (
b000000001 )
b00000001 *
#3
0#
#4
1#
b11111101 '
b01111011 (
b000011000 )
b00011000 *
#5
0#
#6
1#
b11101000 '
b00111000 (
b000101111 )
b00101111 *
#7
0#
#8
1#
b10110010 '
b00001010 (
b001000110 )
b01000110 *
#9
0#
#10
1#
b01101100 '
b00000001 (
b001011101 )
b01011101 *
#11
0#
#12
1#
b00101100 '
b00011110 (
b001110100 )
b01110100 *
#13
0#
#14
1#
b00000101 '
b01011010 (
b010001011 )
b10001011 *
#15
0#
#16
1#
b00000100 '
b10100000 (
b010100010 )
b10100010 *
#17
0#
#18
1#
b00101001 '
b11011101 (
b010111001 )
b10111001 *
#19
0#
#20
1#
b01101001 '
b11111100 (
b011010000 )
b11010000 *
#21
0#
#22
1#
b10101111 '
b11110100 (
b011100111 )
b11100111 *
#23
0#
#24
1#
b11100110 '
b11001000 (
b011111110 )
b11111110 *
#25
0#
#26
1#
b11111101 '
b10000101 (
b000010101 )
b00010101 *
#27
0#
#28
1#
b11101101 '
b01000000 (
b000101100 )
b00101100 *
#29
0#
#30
1#
b10111010 '
b00001110 (
b001000011 )
b01000011 *
#31
0#
#32
1#
b01110101 '
b00000000 (
b001011010 )
b01011010 *
#33
0#
#34
1#
b00110011 '
b00011000 (
b001110001 )
b01110001 *
#35
0#
#36
1#
b00001000 '
b01010001 (
b010001000 )
b10001000 *
#37
0#
#38
1#
b00000010 '
b10010111 (
b010011111 )
b10011111 *
#39
0#
#40
1#
b00100011 '
b11010110 (
b010110110 )
b10110110 *
#41
0#
#42
1#
b01100000 '
b11111010 (
b011001101 )
b11001101 *
#43
0#
#44
1#
b10100110 '
b11110111 (
b011100100 )
b11100100 *
#45
0#
#46
1#
b11100001 '
b11001111 (
b011111011 )
b11111011 *
#47
0#
#48
1#
b11111101 '
b10001110 (
b000010010 )
b00010010 *
#49
0#
#50
1#
b11110001 '
b01001000 (
b000101001 )
b00101001 *
#51
0#
#52
1#
b11000010 '
b00010011 (
b001000000 )
b01000000 *
#53
0#
#54
1#
b01111110 '
b00000000 (
b001010111 )
b01010111 *
#55
0#
#56
1#
b00111011 '
b00010011 (
b001101110 )
b01101110 *
#57
0#
#58
1#
b00001100 '
b01001000 (
b010000101 )
b10000101 *
#59
0#
#60
1#
b00000000 '
b10001110 (
b010011100 )
b10011100 *
#61
0#
#62
1#
b00011100 '
b11001111 (
b010110011 )
b10110011 *
#63
0#
#64
1#
b01010111 '
b11110111 (
b011001010 )
b11001010 *
#65
0#
#66
1#
b10011101 '
b11111010 (
b011100001 )
b11100001 *
#67
0#
#68
1#
b11011010 '
b11010110 (
b011111000 )
b11111000 *
#69
0#
#70
1#
b11111011 '
b10010111 (
b000001111 )
b00001111 *
#71
0#
#72
1#
b11110101 '
b01010001 (
b000100110 )
b00100110 *
#73
0#
#74
1#
b11001010 '
b00011000 (
b000111101 )
b00111101 *
#75
0#
#76
1#
b10001000 '
b00000000 (
b001010100 )
b01010100 *
#77
0#
#78
1#
b01000011 '
b00001110 (
b001101011 )
b01101011 *
#79
0#
#80
1#
b00010000 '
b01000000 (
b010000010 )
b10000010 *
#81
0#
#82
1#
b00000000 '
b10000101 (
b010011001 )
b10011001 *
#83
0#
#84
1#
b00010111 '
b11001000 (
b010110000 )
b10110000 *
#85
0#
#86
1#
b01001110 '
b11110100 (
b011000111 )
b11000111 *
#87
0#
#88
1#
b10010100 '
b11111100 (
b011011110 )
b11011110 *
#89
0#
#90
1#
b11010100 '
b11011101 (
b011110101 )
b11110101 *
#91
0#
#92
1#
b11111001 '
b10100000 (
b000001100 )
b00001100 *
#93
0#
#94
1#
b11111000 '
b01011010 (
b000100011 )
b00100011 *
#95
0#
#96
1#
b11010001 '
b00011110 (
b000111010 )
b00111010 *
#97
0#
#98
1#
b10010001 '
b00000001 (
b001010001 )
b01010001 *
#99
0#
#100
1#
b01001011 '
b00001010 (
b001101000 )
b01101000 *
#101
0#
#102
1#
b00010101 '
b00111000 (
b001111111 )
b01111111 *
#103
0#
#104
1#
b00000000 '
b01111011 (
b010010110 )
b10010110 *
#105
0#
#106
1#
b00010010 '
b11000000 (
b010101101 )
b10101101 *
#107
0#
#108
1#
b01000101 '
b11110000 (
b011000100 )
b11000100 *
#109
0#
#110
1#
b10001011 '
b11111101 (
b011011011 )
b11011011 *
#111
0#
#112
1#
b11001101 '
b11100011 (
b011110010 )
b11110010 *
#113
0#
#114
1#
b11110110 '
b10101001 (
b000001001 )
b00001001 *
#115
0#
#116
1#
b00010110 &
b11111010 '
b01100011 (
b000100000 )
b00100000 *
#117
0#
#118
1#
b00010010 &
b11011000 '
b00100101 (
b000110110 )
b00110110 *
#119
0#
#120
1#
b00001110 &
b10011101 '
b00000011 (
b001001000 )
b01001000 *
#121
0#
#122
1#
b01100110 '
b00000010 (
b001010110 )
b01010110 *
#123
0#
#124
1#
b00111101 '
b00010010 (
b001100100 )
b01100100 *
#125
0#
#126
1#
b00011100 '
b00101110 (
b001110010 )
b01110010 *
#127
0#
#128
1#
b00000111 '
b01010100 (
b010000000 )
b10000000 *
#129
0#
#130
1#
b00000000 '
b01111111 (
b010001110 )
b10001110 *
#131
0#
#132
1#
b00000111 '
b10101001 (
b010011100 )
b10011100 *
#133
0#
#134
1#
b00011100 '
b11001111 (
b010101010 )
b10101010 *
#135
0#
#136
1#
b00111101 '
b11101011 (
b010111000 )
b10111000 *
#137
0#
#138
1#
b00001100 &
b01100110 '
b11111011 (
b011000110 )
b11000110 *
#139
0#
#140
1#
b00001000 &
b10010001 '
b11111100 (
b011010010 )
b11010010 *
#141
0#
#142
1#
b10110101 '
b11110001 (
b011011010 )
b11011010 *
#143
0#
#144
1#
b11001010 '
b11100101 (
b011100010 )
b11100010 *
#145
0#
#146
1#
b11011101 '
b11010100 (
b011101010 )
b11101010 *
#147
0#
#148
1#
b11101011 '
b11000000 (
b011110010 )
b11110010 *
#149
0#
#150
1#
b11110110 '
b10101001 (
b011111010 )
b11111010 *
#151
0#
#152
1#
b11111100 '
b10010001 (
b000000010 )
b00000010 *
#153
0#
#154
1#
b11111101 '
b01111000 (
b000001010 )
b00001010 *
#155
0#
#156
1#
b11111010 '
b01100000 (
b000010010 )
b00010010 *
#157
0#
#158
1#
b11110001 '
b01001000 (
b000011010 )
b00011010 *
#159
0#
#160
1#
b11100101 '
b00110011 (
b000100010 )
b00100010 *
#161
0#
#162
1#
b00000110 &
b11010100 '
b00100000 (
b000101010 )
b00101010 *
#163
0#
#164
1#
b00000010 &
b11000000 '
b00010010 (
b000110000 )
b00110000 *
#165
0#
#166
1#
b00000001 &
b10101111 '
b00001001 (
b000110010 )
b00110010 *
#167
0#
#168
1#
b10101001 '
b00000111 (
b000110011 )
b00110011 *
#169
0#
#170
1#
b10100110 '
b00000110 (
b000110100 )
b00110100 *
#171
0#
#172
1#
b10100011 '
b00000101 (
b000110101 )
b00110101 *
#173
0#
#174
1#
b10100000 '
b00000100 (
b000110110 )
b00110110 *
#175
0#
#176
1#
b10011101 '
b00000011 (
b000110111 )
b00110111 *
#177
0#
#178
1#
b10011010 '
b000111000 )
b00111000 *
#179
0#
#180
1#
b10010111 '
b00000010 (
b000111001 )
b00111001 *
#181
0#
#182
1#
b00000000 &
b10010100 '
b00000001 (
b000111010 )
b00111010 *
#183
0#
#184
1#
b10010001 '
